qasmfmt/__init__.py
qasmfmt/py.typed
qasmfmt-0.0.1.dist-info/METADATA
qasmfmt-0.0.1.dist-info/WHEEL
qasmfmt-0.0.1.dist-info/RECORD
