Metadata-Version: 2.4
Name: qasmfmt
Version: 0.0.1
Summary: OpenQASM 3.0 formatter
Project-URL: Homepage, https://github.com/orangekame3/qasmfmt
Project-URL: Repository, https://github.com/orangekame3/qasmfmt
Author: orangekame3
License: MIT
Keywords: formatter,openqasm,qasm,quantum
Classifier: Development Status :: 2 - Pre-Alpha
Classifier: Intended Audience :: Developers
Classifier: Intended Audience :: Science/Research
Classifier: License :: OSI Approved :: MIT License
Classifier: Programming Language :: Python :: 3
Classifier: Programming Language :: Python :: 3.8
Classifier: Programming Language :: Python :: 3.9
Classifier: Programming Language :: Python :: 3.10
Classifier: Programming Language :: Python :: 3.11
Classifier: Programming Language :: Python :: 3.12
Classifier: Topic :: Scientific/Engineering :: Physics
Classifier: Topic :: Software Development :: Quality Assurance
Requires-Python: >=3.8
